[
  {
    "type": "function",
    "name": "ANVIL_CHAIN_ID",
    "inputs": [],
    "outputs": [
      {
        "name": "",
        "type": "uint256",
        "internalType": "uint256"
      }
    ],
    "stateMutability": "view"
  },
  {
    "type": "function",
    "name": "ANVIL_DEFAULT_ACCOUNT",
    "inputs": [],
    "outputs": [
      {
        "name": "",
        "type": "address",
        "internalType": "address"
      }
    ],
    "stateMutability": "view"
  },
  {
    "type": "function",
    "name": "VRF_FUND_AMOUNT_LINK",
    "inputs": [],
    "outputs": [
      {
        "name": "",
        "type": "uint256",
        "internalType": "uint256"
      }
    ],
    "stateMutability": "view"
  },
  {
    "type": "function",
    "name": "VRF_MOCK_BASE_FEE",
    "inputs": [],
    "outputs": [
      {
        "name": "",
        "type": "uint96",
        "internalType": "uint96"
      }
    ],
    "stateMutability": "view"
  },
  {
    "type": "function",
    "name": "VRF_MOCK_GAS_PRICE_LINK",
    "inputs": [],
    "outputs": [
      {
        "name": "",
        "type": "uint96",
        "internalType": "uint96"
      }
    ],
    "stateMutability": "view"
  },
  {
    "type": "function",
    "name": "VRF_MOCK_WEI_PER_UNIT_LINK",
    "inputs": [],
    "outputs": [
      {
        "name": "",
        "type": "int256",
        "internalType": "int256"
      }
    ],
    "stateMutability": "view"
  },
  {
    "type": "function",
    "name": "VRF_RANDOM_WORDS_COUNT",
    "inputs": [],
    "outputs": [
      {
        "name": "",
        "type": "uint32",
        "internalType": "uint32"
      }
    ],
    "stateMutability": "view"
  }
]